video2pdfslides_tddschn/__init__.py
video2pdfslides_tddschn/cli.py
video2pdfslides_tddschn/utils.py
video2pdfslides_tddschn/video2pdfslides.py
video2pdfslides_tddschn-0.2.2.dist-info/entry_points.txt
video2pdfslides_tddschn-0.2.2.dist-info/LICENSE
video2pdfslides_tddschn-0.2.2.dist-info/WHEEL
video2pdfslides_tddschn-0.2.2.dist-info/METADATA
video2pdfslides_tddschn-0.2.2.dist-info/RECORD
