Metadata-Version: 2.1
Name: video2pdfslides-tddschn
Version: 0.2.2
Summary: Converts a video presentation into a deck of pdf slides by capturing screenshots of unique frames
Home-page: https://github.com/tddschn/video2pdfslides-tddschn
License: MIT
Keywords: video,pdf,slides
Author: Xinyuan Chen
Author-email: 45612704+tddschn@users.noreply.github.com
Requires-Python: >=3.9,<3.10
Classifier: License :: OSI Approved :: MIT License
Classifier: Programming Language :: Python :: 3
Classifier: Programming Language :: Python :: 3.9
Classifier: Topic :: Utilities
Requires-Dist: img2pdf (==0.4.1)
Requires-Dist: imutils (==0.5.4)
Requires-Dist: lxml (>=4.9.1,<5.0.0)
Requires-Dist: opencv-python (==4.5.2.52)
Requires-Dist: pyperclip (>=1.8.2,<2.0.0)
Project-URL: Bug Tracker, https://github.com/tddschn/video2pdfslides-tddschn/issues
Project-URL: Repository, https://github.com/tddschn/video2pdfslides-tddschn
